dl2_reports/__init__.py
dl2_reports/dl2_reports.py
dl2_reports/report.py
dl2_reports/serialization.py
dl2_reports/components/__init__.py
dl2_reports/components/base.py
dl2_reports/components/layout.py
dl2_reports/components/modal.py
dl2_reports/components/page.py
dl2_reports/components/visual.py
dl2_reports/components/visuals/Area.py
dl2_reports/components/visuals/Bar.py
dl2_reports/components/visuals/Boxplot.py
dl2_reports/components/visuals/Card.py
dl2_reports/components/visuals/Checklist.py
dl2_reports/components/visuals/Gauge.py
dl2_reports/components/visuals/Heatmap.py
dl2_reports/components/visuals/Histogram.py
dl2_reports/components/visuals/KPI.py
dl2_reports/components/visuals/Line.py
dl2_reports/components/visuals/Pie.py
dl2_reports/components/visuals/Scatter.py
dl2_reports/components/visuals/Table.py
dl2_reports/components/visuals/__init__.py
dl2_reports/utilities/__init__.py
dl2_reports/utilities/analytics.py
dl2_reports-0.2.10.dist-info/METADATA
dl2_reports-0.2.10.dist-info/WHEEL
dl2_reports-0.2.10.dist-info/top_level.txt
dl2_reports-0.2.10.dist-info/RECORD
