Metadata-Version: 2.4
Name: dl2-reports
Version: 0.2.10
Summary: A Python API for generating Datalys2 reports
Author-email: kameronbrooks <kameron@creation-wasteland.com>
Project-URL: Homepage, https://github.com/kameronbrooks/datalys2-reporting-python-api
Project-URL: Bug Tracker, https://github.com/kameronbrooks/datalys2-reporting-python-api/issues
Classifier: Programming Language :: Python :: 3
Classifier: License :: OSI Approved :: MIT License
Classifier: Operating System :: OS Independent
Requires-Python: >=3.8
Requires-Dist: pandas>=1.0.0
